odoo/addons/purchase_triple_discount/README.rst
odoo/addons/purchase_triple_discount/__init__.py
odoo/addons/purchase_triple_discount/__manifest__.py
odoo/addons/purchase_triple_discount/hooks.py
odoo/addons/purchase_triple_discount/i18n/de.po
odoo/addons/purchase_triple_discount/i18n/es.po
odoo/addons/purchase_triple_discount/i18n/es_MX.po
odoo/addons/purchase_triple_discount/i18n/es_PE.po
odoo/addons/purchase_triple_discount/i18n/fi.po
odoo/addons/purchase_triple_discount/i18n/fr.po
odoo/addons/purchase_triple_discount/i18n/hr.po
odoo/addons/purchase_triple_discount/i18n/it.po
odoo/addons/purchase_triple_discount/i18n/nl_NL.po
odoo/addons/purchase_triple_discount/i18n/pt_BR.po
odoo/addons/purchase_triple_discount/i18n/pt_PT.po
odoo/addons/purchase_triple_discount/i18n/purchase_triple_discount.pot
odoo/addons/purchase_triple_discount/i18n/ro.po
odoo/addons/purchase_triple_discount/i18n/sl.po
odoo/addons/purchase_triple_discount/i18n/zh_CN.po
odoo/addons/purchase_triple_discount/models/__init__.py
odoo/addons/purchase_triple_discount/models/product_supplierinfo.py
odoo/addons/purchase_triple_discount/models/purchase_order.py
odoo/addons/purchase_triple_discount/models/purchase_order_line.py
odoo/addons/purchase_triple_discount/models/triple_discount_mixin.py
odoo/addons/purchase_triple_discount/readme/CONTRIBUTORS.md
odoo/addons/purchase_triple_discount/readme/DESCRIPTION.md
odoo/addons/purchase_triple_discount/readme/USAGE.md
odoo/addons/purchase_triple_discount/static/description/icon.png
odoo/addons/purchase_triple_discount/static/description/index.html
odoo/addons/purchase_triple_discount/tests/__init__.py
odoo/addons/purchase_triple_discount/tests/test_purchase_discount.py
odoo/addons/purchase_triple_discount/views/product_supplierinfo_view.xml
odoo/addons/purchase_triple_discount/views/purchase_view.xml
odoo_addon_purchase_triple_discount-17.0.1.0.0.2.dist-info/METADATA
odoo_addon_purchase_triple_discount-17.0.1.0.0.2.dist-info/WHEEL
odoo_addon_purchase_triple_discount-17.0.1.0.0.2.dist-info/top_level.txt
odoo_addon_purchase_triple_discount-17.0.1.0.0.2.dist-info/RECORD
